RiboCode/GTF_update.py
RiboCode/RPF_count_ORF.py
RiboCode/RiboCode.py
RiboCode/RiboCode_onestep.py
RiboCode/__init__.py
RiboCode/detectORF.py
RiboCode/loadconfig.py
RiboCode/metaplots.py
RiboCode/orf_finder.py
RiboCode/parsing_opts.py
RiboCode/pie_plot.py
RiboCode/plot_orf_density.py
RiboCode/prepare_transcripts.py
RiboCode/process_bam.py
RiboCode/test_func.py
RiboCode/translate_dna.py
RiboCode-1.2.15.dist-info/LICENSE
RiboCode-1.2.15.dist-info/METADATA
RiboCode-1.2.15.dist-info/WHEEL
RiboCode-1.2.15.dist-info/entry_points.txt
RiboCode-1.2.15.dist-info/top_level.txt
RiboCode-1.2.15.dist-info/RECORD
