Metadata-Version: 2.1
Name: RiboCode
Version: 1.2.15
Summary: A package for identifying the translated ORFs using ribosome-profiling data
Home-page: https://github.com/xryanglab/RiboCode
Author: Zhengtao Xiao
Author-email: xzt13@tsinghua.org.cn
License: MIT
Project-URL: Documentation, https://github.com/xryanglab/RiboCode/blob/master/README.rst
Project-URL: Source, https://github.com/xryanglab/RiboCode
Project-URL: ChangeLog, https://github.com/xryanglab/RiboCode/blob/master/ChangeLog.rst
Project-URL: Issues, https://github.com/xryanglab/RiboCode/issues
Keywords: ribo-seq ribosome-profiling ORF
Platform: UNKNOWN
Classifier: Development Status :: 5 - Production/Stable
Classifier: Intended Audience :: Science/Research
Classifier: Topic :: Scientific/Engineering :: Bio-Informatics
Classifier: Environment :: Console
Classifier: Programming Language :: Python :: 2
Classifier: Programming Language :: Python :: 3
License-File: LICENSE
Requires-Dist: pysam (>0.8.4)
Requires-Dist: matplotlib
Requires-Dist: numpy
Requires-Dist: scipy
Requires-Dist: pyfasta
Requires-Dist: biopython
Requires-Dist: h5py (>3.0.0)
Requires-Dist: htseq
Requires-Dist: future
Requires-Dist: statsmodels
Requires-Dist: minepy
